[
  {
    "id": "s1",
    "user": {
      "id": "u2",
      "name": "Charlie",
      "avatar": "/chatapp/media/avatars/u2.jpg"
    },
    "items": [
      {
        "type": "image",
        "src": "/chatapp/media/images/status1.jpg",
        "duration": 5000
      },
      {
        "type": "video",
        "src": "/chatapp/media/images/status2.mp4",
        "duration": 10000
      }
    ],
    "seen": false,
    "ts": "2025-10-25T14:30:00Z"
  },
  {
    "id": "s2",
    "user": {
      "id": "u4",
      "name": "Alex",
      "avatar": "/chatapp/media/avatars/u4.jpg"
    },
    "items": [
      {
        "type": "image",
        "src": "/chatapp/media/images/status3.jpg",
        "duration": 5000
      },
      {
        "type": "video",
        "src": "/chatapp/media/images/status4.mp4",
        "duration": 10000
      }
    ],
    "seen": false,
    "ts": "2025-10-25T10:30:00Z"
  },
  {
    "id": "s3",
    "user": {
      "id": "u6",
      "name": "Jordan",
      "avatar": "/chatapp/media/avatars/u6.jpg"
    },
    "items": [
      {
        "type": "video",
        "src": "/chatapp/media/images/status5.mp4",
        "duration": 10000
      },
      {
        "type": "image",
        "src": "/chatapp/media/images/status6.jpg",
        "duration": 5000
      },
      {
        "type": "image",
        "src": "/chatapp/media/images/status7.jpg",
        "duration": 5000
      }
    ],
    "seen": true,
    "ts": "2025-10-24T20:15:00Z"
  },
  {
    "id": "s4",
    "user": {
      "id": "u7",
      "name": "Taylor",
      "avatar": "/chatapp/media/avatars/u7.jpg"
    },
    "items": [
      {
        "type": "image",
        "src": "/chatapp/media/images/status7.jpg",
        "duration": 5000
      }
    ],
    "seen": true,
    "ts": "2025-10-24T18:00:00Z"
  }
]
